btex/__init__.py
btex-0.4.dist-info/entry_points.txt
btex-0.4.dist-info/METADATA
btex-0.4.dist-info/WHEEL
btex-0.4.dist-info/RECORD
