Metadata-Version: 2.1
Name: btex
Version: 0.4
Summary: A latex's superset
Author: Tyger375
Author-email: edoardo.takanen@gmail.com
Requires-Python: >=3.9,<4.0
Classifier: Programming Language :: Python :: 3
Classifier: Programming Language :: Python :: 3.9
Classifier: Programming Language :: Python :: 3.10
Classifier: Programming Language :: Python :: 3.11
Classifier: Programming Language :: Python :: 3.12
Requires-Dist: watchdog (>=4.0.0,<5.0.0)
